_groupsig.abi3.so
pygroupsig/proof_build.py
pygroupsig/constants.py
pygroupsig/groupsig.py
pygroupsig/memkey.py
pygroupsig/groupsig_build.py
pygroupsig/key_build.py
pygroupsig/klap20_build.py
pygroupsig/mem_key_build.py
pygroupsig/signature.py
pygroupsig/message_build.py
pygroupsig/common_build.py
pygroupsig/mgrkey.py
pygroupsig/exim_build.py
pygroupsig/bld_key_build.py
pygroupsig/gml_build.py
pygroupsig/gml.py
pygroupsig/crl_build.py
pygroupsig/libgroupsig_build.py
pygroupsig/message.py
pygroupsig/identity.py
pygroupsig/trapdoor_build.py
pygroupsig/mgr_key_build.py
pygroupsig/bldkey.py
pygroupsig/proof.py
pygroupsig/__init__.py
pygroupsig/signature_build.py
pygroupsig/blindsig_build.py
pygroupsig/grp_key_build.py
pygroupsig/gl19_build.py
pygroupsig/grpkey.py
pygroupsig/bbs04_build.py
pygroupsig/blindsig.py
pygroupsig/types_build.py
pygroupsig/identity_build.py
pygroupsig/ps16_build.py
pygroupsig-1.1.0.dist-info/RECORD
pygroupsig-1.1.0.dist-info/WHEEL
pygroupsig-1.1.0.dist-info/METADATA
pygroupsig-1.1.0.dist-info/top_level.txt
pygroupsig.libs/libcrypto-021c2f5b.so.1.1
pygroupsig.libs/libssl-6db5df62.so.1.1
pygroupsig.libs/libmcl-0f9f1f0f.so.1.22
pygroupsig.libs/libmclbn384_256-ea5a6755.so.1.22
