Metadata-Version: 2.1
Name: pygroupsig
Version: 1.1.0
Summary: A Python wrapper for libgroupsig
Home-page: https://github.com/IBM/libgroupsig.git
Author: Jesus Diaz Vico
Author-email: jdv@zurich.ibm.com
License: UNKNOWN
Platform: UNKNOWN
Classifier: Programming Language :: Python :: 3
Classifier: License :: OSI Approved :: Apache Software License
Classifier: Operating System :: OS Independent
Requires-Python: >=3
Requires-Dist: cffi
Requires-Dist: path.py
